{"chunk_definitions":[{"row":14,"row_count":1,"visible":true,"expansion_state":0,"options":{"engine":"r","label":"setup","include":false,"dev":"png"},"document_id":"C86105EB","chunk_id":"csetup_chunk","chunk_label":"setup"},{"row":32,"row_count":1,"visible":true,"expansion_state":0,"options":{"engine":"r","label":"include-table_1M","echo":false,"message":false,"warning":false,"results":"asis","dev":"png"},"document_id":"9E6EE2C6","chunk_id":"c5fk2ce3p9rln","chunk_label":"include-table_1M"},{"row":45,"row_count":1,"visible":true,"expansion_state":0,"options":{"engine":"r","label":"include-table_3M","echo":false,"message":false,"warning":false,"results":"asis","dev":"png"},"document_id":"C86105EB","chunk_id":"c88dmw9ziy1cx","chunk_label":"include-table_3M"},{"row":57,"row_count":1,"visible":true,"expansion_state":0,"options":{"engine":"r","label":"include-table_2","echo":false,"message":false,"warning":false,"dev":"png"},"document_id":"C86105EB","chunk_id":"cfqy360x55bia","chunk_label":"include-table_2"},{"row":71,"row_count":1,"visible":true,"expansion_state":0,"options":{"engine":"r","label":"load-image","echo":false,"out.width":"80%","dev":"png"},"document_id":"C86105EB","chunk_id":"cxwhrvcaeazfd","chunk_label":"load-image"}],"doc_write_time":1747763336}